ipn_generator/__init__.py
ipn_generator/generator.py
ipn_generator/tests/__init__.py
ipn_generator/tests/test_IPNGenerator.py
inventree_ipn_generator-0.1.2.dist-info/LICENSE
inventree_ipn_generator-0.1.2.dist-info/METADATA
inventree_ipn_generator-0.1.2.dist-info/WHEEL
inventree_ipn_generator-0.1.2.dist-info/entry_points.txt
inventree_ipn_generator-0.1.2.dist-info/top_level.txt
inventree_ipn_generator-0.1.2.dist-info/RECORD
