Metadata-Version: 2.1
Name: inventree-ipn-generator
Version: 0.1.2
Summary: InvenTree plugin to automatically generate and assign Internal Part Numbers to parts
Author-email: Nichlas Walsøe <lavissawow@gmail.com>
License: MIT License
Project-URL: Homepage, https://github.com/LavissaWoW/inventree-ipn-generator
Classifier: Programming Language :: Python :: 3
Classifier: License :: OSI Approved :: MIT License
Classifier: Operating System :: OS Independent
Requires-Python: >=3.9
License-File: LICENSE
